{
  "bastion_nodes": {
    "sensitive": false,
    "type": [
      "object",
      {
        "bastion-1": "string"
      }
    ],
    "value": {
      "bastion-1": "priv-172-17-0-27.local"
    }
  },
  "control_nodes": {
    "sensitive": false,
    "type": [
      "object",
      {
        "control-1": "string",
        "control-2": "string",
        "control-3": "string"
      }
    ],
    "value": {
      "control-1": "priv-172-17-0-21.local",
      "control-2": "priv-172-17-0-22.local",
      "control-3": "priv-172-17-0-23.local"
    }
  },
  "galera_cluster_nocc": {
    "sensitive": false,
    "type": [
      "object",
      {
        "mariadb01": "string",
        "mariadb02": "string",
        "mariadb03": "string"
      }
    ],
    "value": {
      "mariadb01": "priv-172-17-0-28.local",
      "mariadb02": "priv-172-17-0-29.local",
      "mariadb03": "priv-172-17-0-30.local"
    }
  },
  "haproxy_nodes": {
    "sensitive": false,
    "type": [
      "object",
      {
        "haproxy-primary": "string",
        "haproxy-secondary": "string"
      }
    ],
    "value": {
      "haproxy-primary": "priv-172-17-0-32.local",
      "haproxy-secondary": "priv-172-17-0-33.local"
    }
  },
  "maxscale_servers": {
    "sensitive": false,
    "type": [
      "object",
      {
        "maxscale01": "string"
      }
    ],
    "value": {
      "maxscale01": "priv-172-17-0-31.local"
    }
  },
  "worker_nodes": {
    "sensitive": false,
    "type": [
      "object",
      {
        "worker-1": "string",
        "worker-2": "string",
        "worker-3": "string"
      }
    ],
    "value": {
      "worker-1": "priv-172-17-0-24.local",
      "worker-2": "priv-172-17-0-25.local",
      "worker-3": "priv-172-17-0-26.local"
    }
  }
}
